[
  {
    "hash": "f0d97745df9844e985f3855bd42c9cb07f595798",
    "message": "[Auto] Plan c885dec9 applied",
    "timestamp": 1771446841695,
    "version": "0.0.42"
  },
  {
    "hash": "3de71d6405f070d8c74c9073a4818fbd953fb837",
    "message": "[Auto] Plan 8affb0c4 applied",
    "timestamp": 1771446683033,
    "version": "0.0.41"
  },
  {
    "hash": "29d71e0d24572159292b7ed26500a2a1f3fc0fb9",
    "message": "[Auto] Plan 174ff479 applied",
    "timestamp": 1771446178910,
    "version": "0.0.40"
  }
]